{
  "report_date": "2026-01-06",
  "generated_at": "2026-04-12T10:39:22.268Z",
  "tff_rows": [
    {
      "net": -415904,
      "net_z": -1.4,
      "net_ww": -49063,
      "net_ww_z": -1,
      "long": 128725,
      "long_z": -0.6,
      "long_ww": -14711,
      "long_ww_z": -0.6,
      "short": 544629,
      "short_z": 1.3,
      "short_ww": 34352,
      "short_ww_z": 0.7,
      "flow_state": "",
      "instrument": "标普500",
      "section": "股指",
      "price_chg": 0.7
    },
    {
      "net": -18451,
      "net_z": 0.8,
      "net_ww": 7223,
      "net_ww_z": 0.7,
      "long": 60236,
      "long_z": 0.9,
      "long_ww": 1197,
      "long_ww_z": 0.2,
      "short": 78687,
      "short_z": -0.4,
      "short_ww": -6026,
      "short_ww_z": -0.6,
      "flow_state": "",
      "instrument": "纳斯达克100",
      "section": "股指",
      "price_chg": 0.7
    },
    {
      "net": -14985,
      "net_z": 1,
      "net_ww": 12684,
      "net_ww_z": 1.1,
      "long": 72081,
      "long_z": 0.6,
      "long_ww": 5206,
      "long_ww_z": 0.5,
      "short": 87066,
      "short_z": -0.8,
      "short_ww": -7478,
      "short_ww_z": -0.7,
      "flow_state": "",
      "instrument": "罗素2000",
      "section": "股指",
      "price_chg": 3.29
    },
    {
      "net": 29247,
      "net_z": 0.3,
      "net_ww": -1552,
      "net_ww_z": -0.1,
      "long": 172498,
      "long_z": 1.4,
      "long_ww": 5447,
      "long_ww_z": 0.5,
      "short": 143251,
      "short_z": 1,
      "short_ww": 6999,
      "short_ww_z": 0.4,
      "flow_state": "",
      "instrument": "MSCI新兴市场",
      "section": "股指",
      "price_chg": 4.37
    },
    {
      "net": -5286,
      "net_z": -0.3,
      "net_ww": 958,
      "net_ww_z": 0.1,
      "long": 46869,
      "long_z": 3.5,
      "long_ww": 5897,
      "long_ww_z": 1.6,
      "short": 52155,
      "short_z": 2.5,
      "short_ww": 4939,
      "short_ww_z": 0.9,
      "flow_state": "多空双增",
      "instrument": "MSCI发达市场",
      "section": "股指",
      "price_chg": 1.93
    },
    {
      "net": -786,
      "net_z": -1.4,
      "net_ww": 89,
      "net_ww_z": 0.1,
      "long": 5365,
      "long_z": -0.4,
      "long_ww": -3,
      "long_ww_z": 0,
      "short": 6151,
      "short_z": 2,
      "short_ww": -92,
      "short_ww_z": -0.1,
      "flow_state": "",
      "instrument": "日经225",
      "section": "股指",
      "price_chg": 4.33
    },
    {
      "net": -2247276,
      "net_z": -0.7,
      "net_ww": -27541,
      "net_ww_z": -0.2,
      "long": 520066,
      "long_z": -0.5,
      "long_ww": -32530,
      "long_ww_z": -0.6,
      "short": 2767342,
      "short_z": 0.7,
      "short_ww": -4989,
      "short_ww_z": -0.2,
      "flow_state": "",
      "instrument": "2年期美债",
      "section": "债券",
      "price_chg": 0.01
    },
    {
      "net": -2335739,
      "net_z": -1.3,
      "net_ww": 22398,
      "net_ww_z": 0.4,
      "long": 431405,
      "long_z": 0.4,
      "long_ww": -15814,
      "long_ww_z": -0.4,
      "short": 2767144,
      "short_z": 1.5,
      "short_ww": -38212,
      "short_ww_z": -0.6,
      "flow_state": "",
      "instrument": "10年期美债",
      "section": "债券",
      "price_chg": -0.28
    },
    {
      "net": -588999,
      "net_z": 1.4,
      "net_ww": 27039,
      "net_ww_z": 1.4,
      "long": 100269,
      "long_z": 0,
      "long_ww": -3258,
      "long_ww_z": -0.4,
      "short": 689268,
      "short_z": -1.3,
      "short_ww": -30297,
      "short_ww_z": -1.7,
      "flow_state": "空头回补",
      "instrument": "超长期美债",
      "section": "债券",
      "price_chg": -0.87
    },
    {
      "net": 226872,
      "net_z": 2.1,
      "net_ww": -34708,
      "net_ww_z": -0.5,
      "long": 699961,
      "long_z": 2.1,
      "long_ww": -232089,
      "long_ww_z": -2.7,
      "short": 473089,
      "short_z": -0.8,
      "short_ww": -197381,
      "short_ww_z": -2.3,
      "flow_state": "多空双减",
      "instrument": "联邦基金",
      "section": "利率",
      "price_chg": 0.09
    },
    {
      "net": 50600,
      "net_z": 1.8,
      "net_ww": -2062,
      "net_ww_z": -0.3,
      "long": 119570,
      "long_z": 1.7,
      "long_ww": -1889,
      "long_ww_z": -0.3,
      "short": 68970,
      "short_z": -0.9,
      "short_ww": 173,
      "short_ww_z": 0,
      "flow_state": "",
      "instrument": "欧元/美元",
      "section": "外汇/加密",
      "price_chg": -0.49
    },
    {
      "net": 28947,
      "net_z": 0,
      "net_ww": 3256,
      "net_ww_z": 0.4,
      "long": 60134,
      "long_z": -0.3,
      "long_ww": 3792,
      "long_ww_z": 0.5,
      "short": 31187,
      "short_z": -0.5,
      "short_ww": 536,
      "short_ww_z": 0.1,
      "flow_state": "",
      "instrument": "英镑/美元",
      "section": "外汇/加密",
      "price_chg": 0.17
    },
    {
      "net": -63230,
      "net_z": -0.7,
      "net_ww": 10917,
      "net_ww_z": 1.2,
      "long": 47898,
      "long_z": 1.2,
      "long_ww": 14811,
      "long_ww_z": 2.4,
      "short": 111128,
      "short_z": 1.1,
      "short_ww": 3894,
      "short_ww_z": 0.4,
      "flow_state": "多头建仓",
      "instrument": "日元/美元",
      "section": "外汇/加密",
      "price_chg": -0.39
    },
    {
      "net": 35115,
      "net_z": 2.4,
      "net_ww": 1444,
      "net_ww_z": 0.1,
      "long": 68439,
      "long_z": 2.5,
      "long_ww": 1537,
      "long_ww_z": 0.2,
      "short": 33324,
      "short_z": -1.1,
      "short_ww": 93,
      "short_ww_z": 0,
      "flow_state": "",
      "instrument": "澳元/美元",
      "section": "外汇/加密",
      "price_chg": 0.27
    },
    {
      "net": -11740,
      "net_z": -0.4,
      "net_ww": -829,
      "net_ww_z": -0.7,
      "long": 2554,
      "long_z": -0.4,
      "long_ww": 439,
      "long_ww_z": 0.6,
      "short": 14294,
      "short_z": 0.3,
      "short_ww": 1268,
      "short_ww_z": 1.1,
      "flow_state": "",
      "instrument": "比特币",
      "section": "外汇/加密",
      "price_chg": 5.99
    }
  ],
  "disagg_rows": [
    {
      "net": 24528,
      "net_z": -1.5,
      "net_ww": 8785,
      "net_ww_z": 0.3,
      "long": 148771,
      "long_z": -1.4,
      "long_ww": 2537,
      "long_ww_z": 0.2,
      "short": 124243,
      "short_z": 1.1,
      "short_ww": -6248,
      "short_ww_z": -0.4,
      "flow_state": "",
      "instrument": "WTI原油",
      "section": "能源",
      "price_chg": -1.42
    },
    {
      "net": -101384,
      "net_z": -1.1,
      "net_ww": -17419,
      "net_ww_z": -0.7,
      "long": 195019,
      "long_z": -0.7,
      "long_ww": 23966,
      "long_ww_z": 2,
      "short": 296403,
      "short_z": 0.4,
      "short_ww": 41385,
      "short_ww_z": 1.6,
      "flow_state": "多空双增",
      "instrument": "天然气",
      "section": "能源",
      "price_chg": -15.66
    },
    {
      "net": 68242,
      "net_z": 1.7,
      "net_ww": -2777,
      "net_ww_z": -0.3,
      "long": 75248,
      "long_z": 0,
      "long_ww": -3072,
      "long_ww_z": -0.5,
      "short": 7006,
      "short_z": -2.1,
      "short_ww": -295,
      "short_ww_z": 0,
      "flow_state": "",
      "instrument": "铜",
      "section": "金属",
      "price_chg": 4.94
    },
    {
      "net": 123213,
      "net_z": 0,
      "net_ww": -2827,
      "net_ww_z": -0.2,
      "long": 146445,
      "long_z": -0.6,
      "long_ww": -2197,
      "long_ww_z": -0.2,
      "short": 23232,
      "short_z": -0.9,
      "short_ww": 630,
      "short_ww_z": 0.1,
      "flow_state": "",
      "instrument": "黄金",
      "section": "金属",
      "price_chg": 2.57
    },
    {
      "net": 15822,
      "net_z": -0.5,
      "net_ww": 1814,
      "net_ww_z": 0.3,
      "long": 26978,
      "long_z": -2.4,
      "long_ww": -2122,
      "long_ww_z": -0.4,
      "short": 11156,
      "short_z": -1.2,
      "short_ww": -3936,
      "short_ww_z": -1.1,
      "flow_state": "空头回补",
      "instrument": "白银",
      "section": "金属",
      "price_chg": 4.08
    },
    {
      "net": -12830,
      "net_z": 0.4,
      "net_ww": 9918,
      "net_ww_z": 0.3,
      "long": 225019,
      "long_z": 0.2,
      "long_ww": 5567,
      "long_ww_z": 0.3,
      "short": 237849,
      "short_z": -0.4,
      "short_ww": -4351,
      "short_ww_z": -0.2,
      "flow_state": "",
      "instrument": "玉米",
      "section": "农产品",
      "price_chg": 0.79
    }
  ],
  "price_data": {
    "日经225": {
      "ret": 4.33,
      "ticker": "^N225",
      "date_start": "12-30",
      "date_end": "01-06",
      "px_start": 50339.48046875,
      "px_end": 52518.078125
    },
    "纳斯达克100": {
      "ret": 0.7,
      "ticker": "^NDX",
      "date_start": "12-30",
      "date_end": "01-06",
      "px_start": 25462.560546875,
      "px_end": 25639.7109375
    },
    "2年期美债": {
      "ret": 0.01,
      "ticker": "ZT=F",
      "date_start": "12-30",
      "date_end": "01-06",
      "px_start": 104.359375,
      "px_end": 104.37109375
    },
    "10年期美债": {
      "ret": -0.28,
      "ticker": "ZN=F",
      "date_start": "12-30",
      "date_end": "01-06",
      "px_start": 112.640625,
      "px_end": 112.328125
    },
    "联邦基金": {
      "ret": 0.09,
      "ticker": "ZQ=F",
      "date_start": "12-30",
      "date_end": "01-06",
      "px_start": 96.27749633789062,
      "px_end": 96.36000061035156
    },
    "标普500": {
      "ret": 0.7,
      "ticker": "^GSPC",
      "date_start": "12-30",
      "date_end": "01-06",
      "px_start": 6896.240234375,
      "px_end": 6944.81982421875
    },
    "超长期美债": {
      "ret": -0.87,
      "ticker": "UB=F",
      "date_start": "12-30",
      "date_end": "01-06",
      "px_start": 118.375,
      "px_end": 117.34375
    },
    "WTI原油": {
      "ret": -1.42,
      "ticker": "CL=F",
      "date_start": "12-30",
      "date_end": "01-06",
      "px_start": 57.95000076293945,
      "px_end": 57.130001068115234
    },
    "铜": {
      "ret": 4.94,
      "ticker": "HG=F",
      "date_start": "12-30",
      "date_end": "01-06",
      "px_start": 5.727499961853027,
      "px_end": 6.010499954223633
    },
    "玉米": {
      "ret": 0.79,
      "ticker": "ZC=F",
      "date_start": "12-30",
      "date_end": "01-06",
      "px_start": 440.5,
      "px_end": 444
    },
    "白银": {
      "ret": 4.08,
      "ticker": "SI=F",
      "date_start": "12-30",
      "date_end": "01-06",
      "px_start": 77.3740005493164,
      "px_end": 80.52999877929688
    },
    "黄金": {
      "ret": 2.57,
      "ticker": "GC=F",
      "date_start": "12-30",
      "date_end": "01-06",
      "px_start": 4370.10009765625,
      "px_end": 4482.2001953125
    },
    "罗素2000": {
      "ret": 3.29,
      "ticker": "^RUT",
      "date_start": "12-30",
      "date_end": "01-06",
      "px_start": 2500.590087890625,
      "px_end": 2582.89990234375
    },
    "欧元/美元": {
      "ret": -0.49,
      "ticker": "EURUSD=X",
      "date_start": "12-30",
      "date_end": "01-06",
      "px_start": 1.1772878170013428,
      "px_end": 1.1714951992034912
    },
    "日元/美元": {
      "ret": -0.39,
      "ticker": "JPYUSD=X",
      "date_start": "12-30",
      "date_end": "01-06",
      "px_start": 0.006409722380340099,
      "px_end": 0.0063846358098089695
    },
    "英镑/美元": {
      "ret": 0.17,
      "ticker": "GBPUSD=X",
      "date_start": "12-30",
      "date_end": "01-06",
      "px_start": 1.3510993719100952,
      "px_end": 1.3533997535705566
    },
    "比特币": {
      "ret": 5.99,
      "ticker": "BTC-USD",
      "date_start": "12-30",
      "date_end": "01-06",
      "px_start": 88430.1328125,
      "px_end": 93729.03125
    },
    "澳元/美元": {
      "ret": 0.27,
      "ticker": "AUDUSD=X",
      "date_start": "12-30",
      "date_end": "01-06",
      "px_start": 0.6695501804351807,
      "px_end": 0.6713401079177856
    },
    "天然气": {
      "ret": -15.66,
      "ticker": "NG=F",
      "date_start": "12-30",
      "date_end": "01-06",
      "px_start": 3.9719998836517334,
      "px_end": 3.3499999046325684
    },
    "MSCI新兴市场": {
      "ret": 4.37,
      "ticker": "EEM",
      "date_start": "12-30",
      "date_end": "01-06",
      "px_start": 54.880001068115234,
      "px_end": 57.279998779296875
    },
    "MSCI发达市场": {
      "ret": 1.93,
      "ticker": "EFA",
      "date_start": "12-30",
      "date_end": "01-06",
      "px_start": 96.44000244140625,
      "px_end": 98.30000305175781
    }
  },
  "ai_analysis": "# CFTC持仓报告深度分析（2026-01-06）\n\n## 一、本周核心变化\n\n杠杆基金在标普500期货大幅增加空头34,352手（z=1.3），净空头仓位达-415,904手创3年新高。联邦基金期货出现大规模多空双减，多头减仓232,089手，显示降息预期快速修正。天然气期货多空双增超4万手，市场分歧加剧。\n\n## 二、美股市场\n\n**大盘股指**：标普500净空头仓位z-score达-1.4，处于3年来20%分位数以下，杠杆基金持续看空美股。本周空头大幅增仓34,352手的同时，指数仍上涨0.7%，形成明显的价格与持仓背离。\n\n**成长股**：纳斯达克100净空头仓位有所收敛，空头减仓6,026手，但整体仍维持谨慎态度。\n\n**小盘股**：罗素2000表现最为强劲，同期涨幅3.3%，杠杆基金多头增仓5,206手，空头减仓7,478手，显示对小盘股相对乐观。\n\n**国际市场**：MSCI发达市场出现多空双增（z=3.5和2.5），表明国际股市分歧加大。新兴市场多头仓位达3年高位（z=1.4），配合4.4%涨幅，资金流入趋势明确。\n\n**短期展望**：标普500空头仓位极端化与价格上涨背离，存在空头挤压风险。小盘股和新兴市场相对强势可能延续。\n\n## 三、固收与利率\n\n杠杆基金在收益率曲线上呈现明显的熊市陡峭化押注：2年期净空头-2,247,276手，10年期净空头-2,335,739手（z=-1.3），超长期净空头-588,999手（z=1.4）。\n\n联邦基金期货多空双减规模巨大，多头减仓232,089手，反映市场对美联储降息预期的快速修正。当前净多头226,872手（z=2.1）仍处高位，暗示市场仍预期进一步降息。\n\n超长期债券空头大幅回补30,297手，但债券价格下跌0.9%，显示长端利率上行压力依然存在。这对成长股和高估值资产构成持续压制。\n\n## 四、外汇市场\n\n**美元强势延续**：欧元/美元净多头50,600手（z=1.8）处于高位，但欧元本周下跌0.5%，多头面临考验。澳元/美元净多头35,115手（z=2.4）创3年新高，反映对商品货币的偏好。\n\n**日元异动**：美元/日元多头大幅建仓14,811手（z=1.2），但日元仍升值0.4%，可能反映日本央行政策转向预期。\n\n**套息交易信号**：澳元和欧元的高多头仓位配合美债空头，显示套息交易仍在进行，但面临日元政策风险。\n\n## 五、大宗商品\n\n**能源**：WTI原油净多头24,528手（z=-1.5）处于低位，油价下跌1.4%，反映需求担忧。天然气多空双增超4万手，净空头-101,384手，价格暴跌15.7%，市场极度分化。\n\n**贵金属**：黄金净多头123,213手处于中性水平，价格上涨2.6%表现稳健。白银空头回补3,936手，价格大涨4.1%，工业需求预期改善。\n\n**工业金属**：铜净多头68,242手（z=1.7）处于高位，价格上涨4.9%，反映对全球经济复苏的乐观预期，与新兴市场股市强势呼应。\n\n**农产品**：玉米持仓变化温和，市场相对平静。\n\n## 六、加密货币\n\n比特币期货净空头-11,740手（z=-0.4）处于中性偏空水平，但价格大涨6.0%，显示现货需求强劲。机构投资者态度谨慎，但未能阻止价格上涨，可能面临追涨压力。\n\n## 七、跨市场主题研判\n\n**主题一：政策预期重定价**：联邦基金期货大规模减仓反映降息预期快速修正，配合长端利率上行压力，货币政策紧缩预期升温。这解释了大盘股指空头增加但小盘股相对强势的分化。\n\n**主题二：全球复苏交易重启**：铜价大涨、新兴市场股市强势、商品货币走强形成共振，反映对全球经济复苏的重新定价。这与美国大盘股的谨慎态度形成对比，暗示复苏可能更多体现在美国以外市场。\n\n## 八、风险警示\n\n1. **标普500空头挤压风险**：净空头仓位z-score达-1.4，处于极端水平，若市场继续上涨可能引发大规模空头回补，推动指数快速上行。\n\n2. **天然气市场失控风险**：多空双增超4万手但价格暴跌15.7%，显示供需基本面恶化，可能引发能源板块连锁反应。\n\n3. **利率政策预期反转风险**：联邦基金期货仍有226,872手净多头，若通胀数据超预期或美联储转鹰，可能引发利率市场剧烈调整，冲击所有风险资产。"
}